<?xml version="1.0"?>
<last_names><last_name><value>Hazra</value><date>2009-01-01</date><time>09:17:30</time><os>Linux</os><browser>Chrome 61.0.3163.79</browser><ip>127.0.0.1</ip></last_name><last_name><value>Hazra</value><date>2009-01-01</date><time>10:31:09</time><os>Windows</os><browser>Chrome 61.0.3163.79</browser><ip>127.0.0.1</ip></last_name><last_name><value>Khazra</value><date>2009-01-01</date><time>10:31:26</time><os>Windows</os><browser>Chrome 61.0.3163.79</browser><ip>127.0.0.1</ip></last_name><last_name><value>Hazra</value><date>2009-01-01</date><time>10:32:18</time><os>Windows</os><browser>Chrome 61.0.3163.79</browser><ip>127.0.0.1</ip></last_name><last_name><value>Hazradf</value><date>2009-01-01</date><time>14:49:14</time><os>Windows</os><browser>Chrome 61.0.3163.79</browser><ip>127.0.0.1</ip></last_name><last_name><value>Hazra</value><date>2009-01-01</date><time>14:49:19</time><os>Windows</os><browser>Chrome 61.0.3163.79</browser><ip>127.0.0.1</ip></last_name><last_name><value>Hazra</value><date>2018-04-21</date><time>23:31:35</time><os>Linux - Ubuntu</os><browser>Chrome 65.0.3325.181</browser><ip>127.0.0.1</ip></last_name></last_names>
